{
  "resourceType": "Bundle",
  "id": "FHIR-402",
  "identifier": {
    "system": "https://github.com/microsoft-healthcare-madison/learning-spike-erp/",
    "value": "FHIR-402"
  },
  "type": "collection",
  "timestamp": "2020-04-01T14:01:48.6297921-05:00",
  "entry": [
    {
      "fullUrl": "https://github.com/microsoft-healthcare-madison/learning-spike-erp/MeasureReport/FHIR-403",
      "resource": {
        "resourceType": "MeasureReport",
        "id": "FHIR-403",
        "status": "complete",
        "type": "summary",
        "measure": "http://cdcmeasures.example.org/modules/covid19/20200331/covid-19-test-count",
        "subject": {
          "reference": "Location/Loc-Org-3046",
          "display": "CAMERON MEMORIAL COMMUNITY HOSPITAL INC"
        },
        "date": "2020-04-01T14:01:48.6298271-05:00",
        "reporter": {
          "reference": "Organization/Org-3046",
          "display": "CAMERON MEMORIAL COMMUNITY HOSPITAL INC"
        },
        "period": {
          "start": "2020-03-31",
          "end": "2020-03-31"
        },
        "group": [
          {
            "population": [
              {
                "code": {
                  "coding": [
                    {
                      "code": "measure-population",
                      "display": "Measure Population"
                    }
                  ]
                },
                "count": 30
              }
            ]
          }
        ]
      }
    },
    {
      "fullUrl": "https://github.com/microsoft-healthcare-madison/learning-spike-erp/MeasureReport/FHIR-404",
      "resource": {
        "resourceType": "MeasureReport",
        "id": "FHIR-404",
        "status": "complete",
        "type": "summary",
        "measure": "http://cdcmeasures.example.org/modules/covid19/20200331/covid-19-test-positive-count",
        "subject": {
          "reference": "Location/Loc-Org-3046",
          "display": "CAMERON MEMORIAL COMMUNITY HOSPITAL INC"
        },
        "date": "2020-04-01T14:01:48.6298685-05:00",
        "reporter": {
          "reference": "Organization/Org-3046",
          "display": "CAMERON MEMORIAL COMMUNITY HOSPITAL INC"
        },
        "period": {
          "start": "2020-03-31",
          "end": "2020-03-31"
        },
        "group": [
          {
            "population": [
              {
                "code": {
                  "coding": [
                    {
                      "code": "measure-population",
                      "display": "Measure Population"
                    }
                  ]
                },
                "count": 12
              }
            ]
          }
        ]
      }
    },
    {
      "fullUrl": "https://github.com/microsoft-healthcare-madison/learning-spike-erp/MeasureReport/FHIR-405",
      "resource": {
        "resourceType": "MeasureReport",
        "id": "FHIR-405",
        "status": "complete",
        "type": "summary",
        "measure": "http://cdcmeasures.example.org/modules/covid19/20200331/numTotBeds",
        "subject": {
          "reference": "Location/Loc-Org-3046",
          "display": "CAMERON MEMORIAL COMMUNITY HOSPITAL INC"
        },
        "date": "2020-04-01T14:01:48.6298946-05:00",
        "reporter": {
          "reference": "Organization/Org-3046",
          "display": "CAMERON MEMORIAL COMMUNITY HOSPITAL INC"
        },
        "period": {
          "start": "2020-03-31",
          "end": "2020-03-31"
        },
        "group": [
          {
            "population": [
              {
                "code": {
                  "coding": [
                    {
                      "code": "measure-population",
                      "display": "Measure Population"
                    }
                  ]
                },
                "count": 25
              }
            ]
          }
        ]
      }
    },
    {
      "fullUrl": "https://github.com/microsoft-healthcare-madison/learning-spike-erp/MeasureReport/FHIR-406",
      "resource": {
        "resourceType": "MeasureReport",
        "id": "FHIR-406",
        "status": "complete",
        "type": "summary",
        "measure": "http://cdcmeasures.example.org/modules/covid19/20200331/numbeds",
        "subject": {
          "reference": "Location/Loc-Org-3046",
          "display": "CAMERON MEMORIAL COMMUNITY HOSPITAL INC"
        },
        "date": "2020-04-01T14:01:48.629909-05:00",
        "reporter": {
          "reference": "Organization/Org-3046",
          "display": "CAMERON MEMORIAL COMMUNITY HOSPITAL INC"
        },
        "period": {
          "start": "2020-03-31",
          "end": "2020-03-31"
        },
        "group": [
          {
            "population": [
              {
                "code": {
                  "coding": [
                    {
                      "code": "measure-population",
                      "display": "Measure Population"
                    }
                  ]
                },
                "count": 23
              }
            ]
          }
        ]
      }
    },
    {
      "fullUrl": "https://github.com/microsoft-healthcare-madison/learning-spike-erp/MeasureReport/FHIR-407",
      "resource": {
        "resourceType": "MeasureReport",
        "id": "FHIR-407",
        "status": "complete",
        "type": "summary",
        "measure": "http://cdcmeasures.example.org/modules/covid19/20200331/numBedsOcc",
        "subject": {
          "reference": "Location/Loc-Org-3046",
          "display": "CAMERON MEMORIAL COMMUNITY HOSPITAL INC"
        },
        "date": "2020-04-01T14:01:48.6299237-05:00",
        "reporter": {
          "reference": "Organization/Org-3046",
          "display": "CAMERON MEMORIAL COMMUNITY HOSPITAL INC"
        },
        "period": {
          "start": "2020-03-31",
          "end": "2020-03-31"
        },
        "group": [
          {
            "population": [
              {
                "code": {
                  "coding": [
                    {
                      "code": "measure-population",
                      "display": "Measure Population"
                    }
                  ]
                },
                "count": 7
              }
            ]
          }
        ]
      }
    },
    {
      "fullUrl": "https://github.com/microsoft-healthcare-madison/learning-spike-erp/MeasureReport/FHIR-408",
      "resource": {
        "resourceType": "MeasureReport",
        "id": "FHIR-408",
        "status": "complete",
        "type": "summary",
        "measure": "http://cdcmeasures.example.org/modules/covid19/20200331/numICUBeds",
        "subject": {
          "reference": "Location/Loc-Org-3046",
          "display": "CAMERON MEMORIAL COMMUNITY HOSPITAL INC"
        },
        "date": "2020-04-01T14:01:48.6299373-05:00",
        "reporter": {
          "reference": "Organization/Org-3046",
          "display": "CAMERON MEMORIAL COMMUNITY HOSPITAL INC"
        },
        "period": {
          "start": "2020-03-31",
          "end": "2020-03-31"
        },
        "group": [
          {
            "population": [
              {
                "code": {
                  "coding": [
                    {
                      "code": "measure-population",
                      "display": "Measure Population"
                    }
                  ]
                },
                "count": 2
              }
            ]
          }
        ]
      }
    },
    {
      "fullUrl": "https://github.com/microsoft-healthcare-madison/learning-spike-erp/MeasureReport/FHIR-409",
      "resource": {
        "resourceType": "MeasureReport",
        "id": "FHIR-409",
        "status": "complete",
        "type": "summary",
        "measure": "http://cdcmeasures.example.org/modules/covid19/20200331/numICUBedsOcc",
        "subject": {
          "reference": "Location/Loc-Org-3046",
          "display": "CAMERON MEMORIAL COMMUNITY HOSPITAL INC"
        },
        "date": "2020-04-01T14:01:48.6299507-05:00",
        "reporter": {
          "reference": "Organization/Org-3046",
          "display": "CAMERON MEMORIAL COMMUNITY HOSPITAL INC"
        },
        "period": {
          "start": "2020-03-31",
          "end": "2020-03-31"
        },
        "group": [
          {
            "population": [
              {
                "code": {
                  "coding": [
                    {
                      "code": "measure-population",
                      "display": "Measure Population"
                    }
                  ]
                },
                "count": 1
              }
            ]
          }
        ]
      }
    },
    {
      "fullUrl": "https://github.com/microsoft-healthcare-madison/learning-spike-erp/MeasureReport/FHIR-410",
      "resource": {
        "resourceType": "MeasureReport",
        "id": "FHIR-410",
        "status": "complete",
        "type": "summary",
        "measure": "http://cdcmeasures.example.org/modules/covid19/20200331/numVent",
        "subject": {
          "reference": "Location/Loc-Org-3046",
          "display": "CAMERON MEMORIAL COMMUNITY HOSPITAL INC"
        },
        "date": "2020-04-01T14:01:48.6299639-05:00",
        "reporter": {
          "reference": "Organization/Org-3046",
          "display": "CAMERON MEMORIAL COMMUNITY HOSPITAL INC"
        },
        "period": {
          "start": "2020-03-31",
          "end": "2020-03-31"
        },
        "group": [
          {
            "population": [
              {
                "code": {
                  "coding": [
                    {
                      "code": "measure-population",
                      "display": "Measure Population"
                    }
                  ]
                },
                "count": 1
              }
            ]
          }
        ]
      }
    },
    {
      "fullUrl": "https://github.com/microsoft-healthcare-madison/learning-spike-erp/MeasureReport/FHIR-411",
      "resource": {
        "resourceType": "MeasureReport",
        "id": "FHIR-411",
        "status": "complete",
        "type": "summary",
        "measure": "http://cdcmeasures.example.org/modules/covid19/20200331/numVentUse",
        "subject": {
          "reference": "Location/Loc-Org-3046",
          "display": "CAMERON MEMORIAL COMMUNITY HOSPITAL INC"
        },
        "date": "2020-04-01T14:01:48.629981-05:00",
        "reporter": {
          "reference": "Organization/Org-3046",
          "display": "CAMERON MEMORIAL COMMUNITY HOSPITAL INC"
        },
        "period": {
          "start": "2020-03-31",
          "end": "2020-03-31"
        },
        "group": [
          {
            "population": [
              {
                "code": {
                  "coding": [
                    {
                      "code": "measure-population",
                      "display": "Measure Population"
                    }
                  ]
                },
                "count": 1
              }
            ]
          }
        ]
      }
    },
    {
      "fullUrl": "https://github.com/microsoft-healthcare-madison/learning-spike-erp/MeasureReport/FHIR-412",
      "resource": {
        "resourceType": "MeasureReport",
        "id": "FHIR-412",
        "status": "complete",
        "type": "summary",
        "measure": "http://cdcmeasures.example.org/modules/covid19/20200331/numC19HospPats",
        "subject": {
          "reference": "Location/Loc-Org-3046",
          "display": "CAMERON MEMORIAL COMMUNITY HOSPITAL INC"
        },
        "date": "2020-04-01T14:01:48.6299955-05:00",
        "reporter": {
          "reference": "Organization/Org-3046",
          "display": "CAMERON MEMORIAL COMMUNITY HOSPITAL INC"
        },
        "period": {
          "start": "2020-03-31",
          "end": "2020-03-31"
        },
        "group": [
          {
            "population": [
              {
                "code": {
                  "coding": [
                    {
                      "code": "measure-population",
                      "display": "Measure Population"
                    }
                  ]
                },
                "count": 4
              }
            ]
          }
        ]
      }
    },
    {
      "fullUrl": "https://github.com/microsoft-healthcare-madison/learning-spike-erp/MeasureReport/FHIR-413",
      "resource": {
        "resourceType": "MeasureReport",
        "id": "FHIR-413",
        "status": "complete",
        "type": "summary",
        "measure": "http://cdcmeasures.example.org/modules/covid19/20200331/numC19MechVentPats",
        "subject": {
          "reference": "Location/Loc-Org-3046",
          "display": "CAMERON MEMORIAL COMMUNITY HOSPITAL INC"
        },
        "date": "2020-04-01T14:01:48.6300085-05:00",
        "reporter": {
          "reference": "Organization/Org-3046",
          "display": "CAMERON MEMORIAL COMMUNITY HOSPITAL INC"
        },
        "period": {
          "start": "2020-03-31",
          "end": "2020-03-31"
        },
        "group": [
          {
            "population": [
              {
                "code": {
                  "coding": [
                    {
                      "code": "measure-population",
                      "display": "Measure Population"
                    }
                  ]
                },
                "count": 1
              }
            ]
          }
        ]
      }
    },
    {
      "fullUrl": "https://github.com/microsoft-healthcare-madison/learning-spike-erp/MeasureReport/FHIR-414",
      "resource": {
        "resourceType": "MeasureReport",
        "id": "FHIR-414",
        "status": "complete",
        "type": "summary",
        "measure": "http://cdcmeasures.example.org/modules/covid19/20200331/numC19HOPats",
        "subject": {
          "reference": "Location/Loc-Org-3046",
          "display": "CAMERON MEMORIAL COMMUNITY HOSPITAL INC"
        },
        "date": "2020-04-01T14:01:48.6300214-05:00",
        "reporter": {
          "reference": "Organization/Org-3046",
          "display": "CAMERON MEMORIAL COMMUNITY HOSPITAL INC"
        },
        "period": {
          "start": "2020-03-31",
          "end": "2020-03-31"
        },
        "group": [
          {
            "population": [
              {
                "code": {
                  "coding": [
                    {
                      "code": "measure-population",
                      "display": "Measure Population"
                    }
                  ]
                },
                "count": 0
              }
            ]
          }
        ]
      }
    },
    {
      "fullUrl": "https://github.com/microsoft-healthcare-madison/learning-spike-erp/MeasureReport/FHIR-415",
      "resource": {
        "resourceType": "MeasureReport",
        "id": "FHIR-415",
        "status": "complete",
        "type": "summary",
        "measure": "http://cdcmeasures.example.org/modules/covid19/20200331/numC19OverflowPats",
        "subject": {
          "reference": "Location/Loc-Org-3046",
          "display": "CAMERON MEMORIAL COMMUNITY HOSPITAL INC"
        },
        "date": "2020-04-01T14:01:48.6300343-05:00",
        "reporter": {
          "reference": "Organization/Org-3046",
          "display": "CAMERON MEMORIAL COMMUNITY HOSPITAL INC"
        },
        "period": {
          "start": "2020-03-31",
          "end": "2020-03-31"
        },
        "group": [
          {
            "population": [
              {
                "code": {
                  "coding": [
                    {
                      "code": "measure-population",
                      "display": "Measure Population"
                    }
                  ]
                },
                "count": 0
              }
            ]
          }
        ]
      }
    },
    {
      "fullUrl": "https://github.com/microsoft-healthcare-madison/learning-spike-erp/MeasureReport/FHIR-416",
      "resource": {
        "resourceType": "MeasureReport",
        "id": "FHIR-416",
        "status": "complete",
        "type": "summary",
        "measure": "http://cdcmeasures.example.org/modules/covid19/20200331/numC19OFMechVentPats",
        "subject": {
          "reference": "Location/Loc-Org-3046",
          "display": "CAMERON MEMORIAL COMMUNITY HOSPITAL INC"
        },
        "date": "2020-04-01T14:01:48.630047-05:00",
        "reporter": {
          "reference": "Organization/Org-3046",
          "display": "CAMERON MEMORIAL COMMUNITY HOSPITAL INC"
        },
        "period": {
          "start": "2020-03-31",
          "end": "2020-03-31"
        },
        "group": [
          {
            "population": [
              {
                "code": {
                  "coding": [
                    {
                      "code": "measure-population",
                      "display": "Measure Population"
                    }
                  ]
                },
                "count": 1
              }
            ]
          }
        ]
      }
    },
    {
      "fullUrl": "https://github.com/microsoft-healthcare-madison/learning-spike-erp/MeasureReport/FHIR-417",
      "resource": {
        "resourceType": "MeasureReport",
        "id": "FHIR-417",
        "status": "complete",
        "type": "summary",
        "measure": "http://cdcmeasures.example.org/modules/covid19/20200331/covid-19-recovered",
        "subject": {
          "reference": "Location/Loc-Org-3046",
          "display": "CAMERON MEMORIAL COMMUNITY HOSPITAL INC"
        },
        "date": "2020-04-01T14:01:48.6300643-05:00",
        "reporter": {
          "reference": "Organization/Org-3046",
          "display": "CAMERON MEMORIAL COMMUNITY HOSPITAL INC"
        },
        "period": {
          "start": "2020-03-31",
          "end": "2020-03-31"
        },
        "group": [
          {
            "population": [
              {
                "code": {
                  "coding": [
                    {
                      "code": "measure-population",
                      "display": "Measure Population"
                    }
                  ]
                },
                "count": 0
              }
            ]
          }
        ]
      }
    },
    {
      "fullUrl": "https://github.com/microsoft-healthcare-madison/learning-spike-erp/MeasureReport/FHIR-418",
      "resource": {
        "resourceType": "MeasureReport",
        "id": "FHIR-418",
        "status": "complete",
        "type": "summary",
        "measure": "http://cdcmeasures.example.org/modules/covid19/20200331/numC19Died",
        "subject": {
          "reference": "Location/Loc-Org-3046",
          "display": "CAMERON MEMORIAL COMMUNITY HOSPITAL INC"
        },
        "date": "2020-04-01T14:01:48.630078-05:00",
        "reporter": {
          "reference": "Organization/Org-3046",
          "display": "CAMERON MEMORIAL COMMUNITY HOSPITAL INC"
        },
        "period": {
          "start": "2020-03-31",
          "end": "2020-03-31"
        },
        "group": [
          {
            "population": [
              {
                "code": {
                  "coding": [
                    {
                      "code": "measure-population",
                      "display": "Measure Population"
                    }
                  ]
                },
                "count": 0
              }
            ]
          }
        ]
      }
    }
  ]
}